contextshare/__init__.py
contextshare/contextshare.py
contextshare-0.1.1.dist-info/LICENSE
contextshare-0.1.1.dist-info/METADATA
contextshare-0.1.1.dist-info/WHEEL
contextshare-0.1.1.dist-info/top_level.txt
contextshare-0.1.1.dist-info/RECORD
