Metadata-Version: 2.1
Name: contextshare
Version: 0.1.1
Summary: Simple interface for numpy arrays in multiprocessing contexts.
Home-page: https://github.com/ferchault/contextshare
Author: Guido Falk von Rudorff
Author-email: guido@vonrudorff.de
License: MIT license
Keywords: contextshare
Platform: UNKNOWN
Classifier: Development Status :: 2 - Pre-Alpha
Classifier: Intended Audience :: Developers
Classifier: License :: OSI Approved :: MIT License
Classifier: Natural Language :: English
Classifier: Programming Language :: Python :: 3
Classifier: Programming Language :: Python :: 3.7
Classifier: Programming Language :: Python :: 3.8
Requires-Python: >=3.8
